qstd_logger_json_formatter/__init__.py
qstd_logger_json_formatter-0.3.0.dist-info/LICENSE
qstd_logger_json_formatter-0.3.0.dist-info/METADATA
qstd_logger_json_formatter-0.3.0.dist-info/WHEEL
qstd_logger_json_formatter-0.3.0.dist-info/top_level.txt
qstd_logger_json_formatter-0.3.0.dist-info/RECORD
