Metadata-Version: 2.1
Name: qstd-logger-json-formatter
Version: 0.3.0
Summary: Logging json formatter
Home-page: https://github.com/QuisEgoSum/qstd-logger-json-formatter
Author: QuisEgoSum
Author-email: subbotin.evdokim@gmail.com
License: MIT
Keywords: logging json formatter
Requires-Python: >=3.7
License-File: LICENSE
